testcase_converter/__init__.py
testcase_converter/converter.py
testcase_converter/resources/template.xmind
testcase_converter-0.4.0.dist-info/METADATA
testcase_converter-0.4.0.dist-info/WHEEL
testcase_converter-0.4.0.dist-info/entry_points.txt
testcase_converter-0.4.0.dist-info/top_level.txt
testcase_converter-0.4.0.dist-info/RECORD
