Metadata-Version: 2.4
Name: testcase-converter
Version: 0.4.0
Summary: Convert test cases between Excel and XMind formats with enhanced features
Home-page: https://github.com/misldy/TestCaseConverter
Author: TestCaseConverter Contributors
Author-email: testcase-converter@example.com
Classifier: Programming Language :: Python :: 3
Classifier: License :: OSI Approved :: MIT License
Classifier: Operating System :: OS Independent
Classifier: Topic :: Software Development :: Testing
Classifier: Topic :: Office/Business
Classifier: Intended Audience :: Developers
Requires-Python: >=3.7
Requires-Dist: xmind
Requires-Dist: openpyxl>=3.0.0
Requires-Dist: dataclasses; python_version < "3.7"
Dynamic: author
Dynamic: author-email
Dynamic: classifier
Dynamic: description
Dynamic: description-content-type
Dynamic: home-page
Dynamic: requires-dist
Dynamic: requires-python
Dynamic: summary
